dclex/__init__.py
dclex/dclex.py
dclex/dclex_client.py
dclex/settings.py
dclex/types.py
dclex/resources/digital_identity_contract_abi.json
dclex/resources/factory_contract_abi.json
dclex/resources/usdc_contract_abi.json
dclex/resources/vault_contract_abi.json
dclex-0.0.13.dist-info/LICENSE
dclex-0.0.13.dist-info/METADATA
dclex-0.0.13.dist-info/WHEEL
dclex-0.0.13.dist-info/top_level.txt
dclex-0.0.13.dist-info/RECORD
