Metadata-Version: 2.1
Name: dclex
Version: 0.0.13
Summary: DCLEX python library
License: DCLEX API Non-Commercial License
Classifier: Intended Audience :: Financial and Insurance Industry
Classifier: Programming Language :: Python :: 3.7
Classifier: Programming Language :: Python :: 3.8
Classifier: Programming Language :: Python :: 3.9
Classifier: Programming Language :: Python :: 3.10
Classifier: Programming Language :: Python :: 3.11
Classifier: Programming Language :: Python :: 3.12
Requires-Python: >=3.7
License-File: LICENSE
Requires-Dist: web3 ==6.19.0
Requires-Dist: siwe ==2.4.1
Requires-Dist: requests ==2.32.3
Requires-Dist: sseclient ==0.0.27
